<xml>
	<dados>
		<postagem>
			<titulo>AIDE - WEBVIEW</titulo>
			<descricao>APRENDA A UTILIZAR O COMPONENTE WEBVIEW E EXIBIR PÁGINAS DA INTERNET DENTRO DO SEU APLICATIVO.</descricao>
			<imagem></imagem>
			<conteudo>OLÁ, AMIGO. SEJA MUITO BEM VINDO AO APLICATIVO JTutors. NESTE TUTORIAL VOCÊ VAI PRENDER A UTILIZAR O COMPONENTE WEBVIEW PARA MOSTRAR PÁGINAS DA INTERNET DENTRO DO SEU APLICATIVO SEM NECESSIDADE DE UM NAVEGADOR EXTERNO. ENTÃO FIQUE COM O VÍDEO TUTORIAL E BOA PROGRAMAÇÃO.</conteudo>
			<id>a6BcASM3HSI</id>
		</postagem>
	</dados>
</xml>